.travis.yml
AUTHORS
ChangeLog
LICENSE
README.rst
pytest.ini
requirements.txt
setup.cfg
setup.py
test-requirements.txt
tox.ini
easytrakt/__init__.py
easytrakt/generator.py
easytrakt/models.py
easytrakt.egg-info/PKG-INFO
easytrakt.egg-info/SOURCES.txt
easytrakt.egg-info/dependency_links.txt
easytrakt.egg-info/not-zip-safe
easytrakt.egg-info/pbr.json
easytrakt.egg-info/requires.txt
easytrakt.egg-info/top_level.txt
tests/integration/conftest.py
tests/integration/test_data_retrieval.py
tests/unit/conftest.py
tests/unit/test_data_retrieval.py