Metadata-Version: 1.1
Name: easytrakt
Version: 0.1.6
Summary: simple client for Trakt.TV api
Home-page: https://github.com/lad1337/easytrakt
Author: Dennis Lutter
Author-email: lad1337@gmail.com
License: UNKNOWN
Platform: UNKNOWN
Classifier: Environment :: Console
Classifier: Intended Audience :: Developers
Classifier: License :: OSI Approved :: GNU General Public License v3 (GPLv3)
Classifier: Operating System :: POSIX :: Linux
Classifier: Operating System :: MacOS :: MacOS X
Classifier: Programming Language :: Python
Classifier: Programming Language :: Python :: 2.7
Classifier: Topic :: Software Development :: Libraries
